XForce/__init__.py
XForce/details/__init__.py
XForce-0.8.dist-info/LICENSE
XForce-0.8.dist-info/METADATA
XForce-0.8.dist-info/WHEEL
XForce-0.8.dist-info/top_level.txt
XForce-0.8.dist-info/RECORD
