Metadata-Version: 2.1
Name: XForce
Version: 0.8
Summary: IBM Security utilitary library in python. Search and query all sources: threat_activities and groups, malware_analysis, industries 
Home-page: https://github.com/Jul10l1r4/x-force
Author: Julio Lira
Author-email: jul10l1r4@disroot.org
License: GPLv3
Keywords: threat intelligence security ibm xforce x-force blueteam search query api exchange otx cti oct
Classifier: Programming Language :: Python :: 3
Classifier: License :: OSI Approved :: GNU General Public License v3 or later (GPLv3+)
Classifier: Operating System :: OS Independent
Classifier: Topic :: Internet
Classifier: Topic :: Security
License-File: LICENSE
